LICENSE
MANIFEST.in
README.md
setup.py
tdxwiyqvef/__init__.py
tdxwiyqvef/api_helper.py
tdxwiyqvef/configuration.py
tdxwiyqvef/decorators.py
tdxwiyqvef/tdxwiyqvef_client.py
tdxwiyqvef.egg-info/PKG-INFO
tdxwiyqvef.egg-info/SOURCES.txt
tdxwiyqvef.egg-info/dependency_links.txt
tdxwiyqvef.egg-info/requires.txt
tdxwiyqvef.egg-info/top_level.txt
tdxwiyqvef/controllers/__init__.py
tdxwiyqvef/controllers/api_controller.py
tdxwiyqvef/controllers/base_controller.py
tdxwiyqvef/exceptions/__init__.py
tdxwiyqvef/exceptions/api_exception.py
tdxwiyqvef/http/__init__.py
tdxwiyqvef/http/http_call_back.py
tdxwiyqvef/http/http_client.py
tdxwiyqvef/http/http_context.py
tdxwiyqvef/http/http_method_enum.py
tdxwiyqvef/http/http_request.py
tdxwiyqvef/http/http_response.py
tdxwiyqvef/http/requests_client.py
tdxwiyqvef/http/auth/__init__.py
tdxwiyqvef/http/auth/basic_auth.py
tdxwiyqvef/models/__init__.py
tdxwiyqvef/models/suite_code_enum.py
tests/__init__.py
tests/http_response_catcher.py
tests/test_helper.py
tests/controllers/__init__.py
tests/controllers/controller_test_base.py
tests/controllers/test_api_controller.py